authapi
